tenable_was/__init__.py
tenable_was/py.typed
tenable_was-0.3.0.dist-info/METADATA
tenable_was-0.3.0.dist-info/WHEEL
tenable_was-0.3.0.dist-info/RECORD
