Metadata-Version: 2.4
Name: tenable-was
Version: 0.3.0
Summary: Python client for Tenable Web Application Scanning (WAS) API
Author-email: Alec Meyer <abmeyer@stackarmor.com>, Megha Patel <mpatel@stackarmor.com>
Requires-Python: >=3.11
Requires-Dist: requests>=2.32.3
